pycozo_async/__init__.py
pycozo_async/builder.py
pycozo_async/client.py
pycozo_async/client_patch.py
pycozo_async/ext_impl.py
pycozo_async/ipyext.py
pycozo_async/ipyext_direct.py
pycozo_async/test_builder.py
pycozo_async/test_client.py
pycozo_async-0.7.7.dist-info/LICENSE.txt
pycozo_async-0.7.7.dist-info/METADATA
pycozo_async-0.7.7.dist-info/WHEEL
pycozo_async-0.7.7.dist-info/RECORD
