Metadata-Version: 2.1
Name: pycozo-async
Version: 0.7.7
Summary: 
Author: Julep AI developers
Author-email: developers@julep.ai
Requires-Python: >=3.10,<4.0
Classifier: Programming Language :: Python :: 3
Classifier: Programming Language :: Python :: 3.10
Classifier: Programming Language :: Python :: 3.11
Classifier: Programming Language :: Python :: 3.12
Classifier: Programming Language :: Python :: 3.13
Requires-Dist: cozo-embedded (>=0.7.6,<0.8.0)
Requires-Dist: httpx (>=0.27.2,<0.28.0)
Requires-Dist: ipython (>=8.29.0,<9.0.0)
Requires-Dist: pandas (>=2.2.3,<3.0.0)
